llama_index/tools/valyu/__init__.py
llama_index/tools/valyu/base.py
llama_index/tools/valyu/retriever.py
llama_index_tools_valyu-0.5.0.dist-info/METADATA
llama_index_tools_valyu-0.5.0.dist-info/WHEEL
llama_index_tools_valyu-0.5.0.dist-info/RECORD
