Metadata-Version: 2.4
Name: llama-index-tools-valyu
Version: 0.5.0
Summary: llama-index tools valyu integration
Author-email: Alex Ng <alexander.ng@valyu.network>
Maintainer: alexngys
License-Expression: MIT
Requires-Python: <4.0,>=3.9
Requires-Dist: llama-index-core<0.15,>=0.13.0
Requires-Dist: valyu>=2.0.3
